{
    "Proverbs_27_17_versions": [
        {
            "text": "As iron sharpens iron, so one person sharpens another.",
            "translation": "New International Version (NIV)"
        },
        {
            "text": "Iron sharpens iron, and one man sharpens another.",
            "translation": "English Standard Version (ESV)"
        },
        {
            "text": "As iron sharpens iron, so a friend sharpens a friend.",
            "translation": "New Living Translation (NLT)"
        },
        {
            "text": "Iron sharpens iron; so a man sharpens the countenance of his friend.",
            "translation": "King James Version (KJV)"
        },
        {
            "text": "Iron sharpeneth iron; so a man sharpeneth the countenance of his friend.",
            "translation": "American Standard Version (ASV)"
        },
        {
            "text": "Just as iron sharpens iron, a person sharpens the character of his friend.",
            "translation": "Common English Bible (CEB)"
        },
        {
            "text": "In the same way that iron sharpens iron, a person sharpens the character of their friend.",
            "translation": "Complete Jewish Bible (CJB)"
        }
    ]
}
